{
    "local": {
        "registry_endpoint": "https://some-endpoint.com",
        "registry_api_key": "some-guid-goes-here",
        "dataset_id": "some-guid",
        "services_resource_id": "some guid",
        "standards_resource_id": "some guid"
    },
    "staging": {
        "registry_endpoint": "https://some-endpoint.com",
        "registry_api_key": "some-guid-goes-here",
        "dataset_id": "some-guid",
        "services_resource_id": "some guid",
        "standards_resource_id": "some guid"
    },
    "production": {
        "registry_endpoint": "https://some-endpoint.com",
        "registry_api_key": "some-guid-goes-here",
        "dataset_id": "some-guid",
        "services_resource_id": "some guid",
        "standards_resource_id": "some guid"
    }
}